LICENSE.txt
README.md
setup.py
pocketKnife/__init__.py
pocketKnife/pocketKnife.py
pocketKnife.egg-info/PKG-INFO
pocketKnife.egg-info/SOURCES.txt
pocketKnife.egg-info/dependency_links.txt
pocketKnife.egg-info/requires.txt
pocketKnife.egg-info/top_level.txt